lino_welcht/__init__.py
lino_welcht/help_texts.py
lino_welcht/layouts.py
lino_welcht/migrate.py
lino_welcht/settings.py
lino_welcht/workflows.py
lino_welcht/lib/__init__.py
lino_welcht/lib/courses/__init__.py
lino_welcht/lib/courses/models.py
lino_welcht/lib/courses/ui.py
lino_welcht/lib/courses/config/courses/Enrolment/enrolment.body.html
lino_welcht/lib/courses/config/courses/Enrolment/intervention.body.html
lino_welcht/lib/courses/fixtures/__init__.py
lino_welcht/lib/courses/fixtures/demo.py
lino_welcht/lib/courses/fixtures/std.py
lino_welcht/lib/cv/__init__.py
lino_welcht/lib/cv/models.py
lino_welcht/lib/cv/fixtures/__init__.py
lino_welcht/lib/cv/fixtures/demo.py
lino_welcht/lib/cv/fixtures/std.py
lino_welcht/lib/isip/__init__.py
lino_welcht/lib/isip/models.py
lino_welcht/lib/pcsw/__init__.py
lino_welcht/lib/pcsw/choicelists.py
lino_welcht/lib/pcsw/models.py
lino_welcht/lib/pcsw/config/pcsw/Coaching/coaching.body.html
lino_welcht/lib/pcsw/fixtures/__init__.py
lino_welcht/lib/pcsw/fixtures/demo2.py
lino_welcht/lib/pcsw/fixtures/std.py
lino_welcht/locale/django.pot
lino_welcht/locale/de/LC_MESSAGES/django.mo
lino_welcht/locale/de/LC_MESSAGES/django.po
lino_welcht/locale/fr/LC_MESSAGES/django.mo
lino_welcht/locale/fr/LC_MESSAGES/django.po
lino_welcht/locale/nl/LC_MESSAGES/django.mo
lino_welcht/locale/nl/LC_MESSAGES/django.po
lino_welcht-25.11.0.dist-info/METADATA
lino_welcht-25.11.0.dist-info/WHEEL
lino_welcht-25.11.0.dist-info/licenses/AUTHORS.rst
lino_welcht-25.11.0.dist-info/licenses/AUTHORS.rst~
lino_welcht-25.11.0.dist-info/licenses/COPYING
lino_welcht-25.11.0.dist-info/licenses/COPYING~
lino_welcht-25.11.0.dist-info/RECORD
